chessimg2pos/__init__.py
chessimg2pos/chessboard_finder.py
chessimg2pos/chessboard_image.py
chessimg2pos/chessclassifier.py
chessimg2pos/chessdataset.py
chessimg2pos/generate_chessboards.py
chessimg2pos/generate_tiles.py
chessimg2pos/model_loader.py
chessimg2pos/predictor.py
chessimg2pos/trainer.py
chessimg2pos/utils.py
chessimg2pos/view_images.py
chessimg2pos-0.1.4.dist-info/METADATA
chessimg2pos-0.1.4.dist-info/WHEEL
chessimg2pos-0.1.4.dist-info/licenses/LICENCE
chessimg2pos-0.1.4.dist-info/RECORD
