Metadata-Version: 2.3
Name: chessimg2pos
Version: 0.1.4
Summary: Recognize chess positions from board images using deep learning
Project-URL: Homepage, https://github.com/mdicio/chessimg2pos
Project-URL: Repository, https://github.com/mdicio/chessimg2pos
Project-URL: Issues, https://github.com/mdicio/chessimg2pos/issues
Author-email: Marco Di Ciò <marcodicio.md@gmail.com>
License: MIT
Keywords: FEN,PyTorch,chess,computer vision,deep learning
Classifier: Development Status :: 3 - Alpha
Classifier: Intended Audience :: Developers
Classifier: Intended Audience :: Education
Classifier: License :: OSI Approved :: MIT License
Classifier: Programming Language :: Python :: 3
Classifier: Programming Language :: Python :: 3.10
Classifier: Programming Language :: Python :: 3.11
Classifier: Topic :: Games/Entertainment :: Board Games
Classifier: Topic :: Scientific/Engineering :: Artificial Intelligence
Classifier: Topic :: Software Development :: Libraries :: Python Modules
Requires-Python: >=3.10
Requires-Dist: matplotlib
Requires-Dist: numpy
Requires-Dist: pandas
Requires-Dist: pillow
Requires-Dist: requests
Requires-Dist: torch
Requires-Dist: torchvision
